binwise/__init__.py
binwise/model.py
binwise/utils.py
binwise/tests/__init__.py
binwise/tests/test_model.py
binwise/tests/test_utils.py
binwise-0.2.0.dist-info/LICENSE
binwise-0.2.0.dist-info/METADATA
binwise-0.2.0.dist-info/WHEEL
binwise-0.2.0.dist-info/top_level.txt
binwise-0.2.0.dist-info/RECORD
